srunner/__init__.py
srunner/challenge/__init__.py
srunner/challenge/challenge_evaluator_routes.py
srunner/challenge/challenge_statistics_manager.py
srunner/challenge/test_challenge_route.py
srunner/challenge/test_routes.py
srunner/challenge/autoagents/DummyAgent.py
srunner/challenge/autoagents/HumanAgent.py
srunner/challenge/autoagents/NPCAgent.py
srunner/challenge/autoagents/Track4SampleAgent.py
srunner/challenge/autoagents/__init__.py
srunner/challenge/autoagents/agent_wrapper.py
srunner/challenge/autoagents/autonomous_agent.py
srunner/challenge/autoagents/dummy_agent.py
srunner/challenge/autoagents/human_agent.py
srunner/challenge/autoagents/npc_agent.py
srunner/challenge/autoagents/ros_agent.py
srunner/challenge/autoagents/track_4_sample_agent.py
srunner/challenge/envs/__init__.py
srunner/challenge/envs/scene_layout_sensors.py
srunner/challenge/envs/sensor_interface.py
srunner/challenge/envs/server_manager.py
srunner/challenge/utils/__init__.py
srunner/challenge/utils/route_configuration_parser.py
srunner/challenge/utils/route_manipulation.py
srunner/scenarioconfigs/__init__.py
srunner/scenarioconfigs/openscenario_configuration.py
srunner/scenarioconfigs/route_scenario_configuration.py
srunner/scenarioconfigs/scenario_configuration.py
srunner/scenariomanager/__init__.py
srunner/scenariomanager/atomic_scenario_behavior.py
srunner/scenariomanager/atomic_scenario_criteria.py
srunner/scenariomanager/carla_data_provider.py
srunner/scenariomanager/result_writer.py
srunner/scenariomanager/scenario_manager.py
srunner/scenariomanager/timer.py
srunner/scenariomanager/traffic_events.py
srunner/scenariomanager/scenarioatomics/__init__.py
srunner/scenariomanager/scenarioatomics/atomic_behaviors.py
srunner/scenariomanager/scenarioatomics/atomic_criteria.py
srunner/scenariomanager/scenarioatomics/atomic_trigger_conditions.py
srunner/scenarios/__init__.py
srunner/scenarios/background_activity.py
srunner-0.15.dist-info/METADATA
srunner-0.15.dist-info/RECORD
srunner-0.15.dist-info/WHEEL
srunner-0.15.dist-info/top_level.txt
