Metadata-Version: 2.1
Name: srunner
Version: 0.15
Summary: The package in order to use scenarios for CARLA
Home-page: https://github.com/carla-simulator/scenario_runner
Author: Carla Team
Author-email: carla.simulatort@gmail.com
License: UNKNOWN
Platform: UNKNOWN
Classifier: Programming Language :: Python :: 3
Classifier: License :: OSI Approved :: MIT License
Classifier: Operating System :: OS Independent
